RSSparser/RSSFeed.py
RSSparser/RSSItems.py
RSSparser/__init__.py
RSSparser/cache_news.py
RSSparser/convert_format.py
RSSparser/date_time.py
RSSparser/fetch_data.py
RSSparser/prepare_data.py
RSSparser/print_news.py
RSSparser/rss_parser.py
rss_parser_celine_trial1-5.1.0.dist-info/LICENSE
rss_parser_celine_trial1-5.1.0.dist-info/METADATA
rss_parser_celine_trial1-5.1.0.dist-info/WHEEL
rss_parser_celine_trial1-5.1.0.dist-info/entry_points.txt
rss_parser_celine_trial1-5.1.0.dist-info/top_level.txt
rss_parser_celine_trial1-5.1.0.dist-info/RECORD
