Metadata-Version: 2.1
Name: rss-parser-celine-trial1
Version: 5.1.0
Summary: RSS-parser is a command line interface RSS feed reader
Author: Celine Hovanessian Far
Author-email: celien.hovanessian@gmail.com
License: UNKNOWN
Keywords: rss,rss parser,rss feed,news
Platform: UNKNOWN
Classifier: License :: OSI Approved :: MIT License
Classifier: Natural Language :: English
Classifier: Operating System :: OS Independent
Classifier: Programming Language :: Python
Classifier: Programming Language :: Python :: 3
Classifier: Programming Language :: Python :: 3.9
Classifier: Topic :: Education
Requires-Python: >=3.7
License-File: LICENSE
Requires-Dist: sphinx-rtd-theme
Requires-Dist: beautifulsoup4 (==4.11.1)
Requires-Dist: python-dateutil (==2.8.2)
Requires-Dist: reportlab (==3.6.9)
Requires-Dist: requests (==2.27.1)
